cruds/__init__.py
cruds/auth.py
cruds/core.py
cruds/exception.py
cruds/interface.py
cruds/interface_schema.yaml
cruds/interfaces/planhat/__init__.py
cruds/interfaces/planhat/configuration.yaml
cruds/interfaces/planhat/exception.py
cruds/interfaces/planhat/logic.py
cruds-1.4.2.dist-info/licenses/LICENSE
cruds-1.4.2.dist-info/METADATA
cruds-1.4.2.dist-info/WHEEL
cruds-1.4.2.dist-info/top_level.txt
cruds-1.4.2.dist-info/RECORD
