Metadata-Version: 2.4
Name: cruds
Version: 1.4.2
Summary: CRUDs is a high level library for API's, and is ideal for automation system and/or interactive environments like Notebooks
Home-page: https://github.com/johnbrandborg/cruds
Author: John Brandborg
Author-email: john.brandborg+pypi@pm.me
License: MIT
Project-URL: Changelog, http://cruds.readthedocs.io/en/stable/changelog.html
Project-URL: Documentation, http://cruds.readthedocs.io/en/stable
Project-URL: Source, https://github.com/johnbrandborg/cruds
Project-URL: Tracker, https://github.com/johnbrandborg/cruds/issues
Keywords: rest api crud http https planhat
Platform: unix
Platform: linux
Platform: osx
Platform: cygwin
Platform: win32
Classifier: Development Status :: 5 - Production/Stable
Classifier: Intended Audience :: Developers
Classifier: Environment :: Console
Classifier: License :: OSI Approved :: MIT License
Classifier: Operating System :: MacOS :: MacOS X
Classifier: Operating System :: Microsoft :: Windows
Classifier: Operating System :: POSIX
Classifier: Programming Language :: Python :: 3
Classifier: Programming Language :: Python :: 3 :: Only
Classifier: Programming Language :: Python :: 3.9
Classifier: Programming Language :: Python :: 3.10
Classifier: Programming Language :: Python :: 3.11
Classifier: Programming Language :: Python :: 3.12
Classifier: Topic :: Software Development :: Libraries
Classifier: Topic :: Utilities
Requires-Python: <4.0.0,>=3.9
License-File: LICENSE
Requires-Dist: certifi>=2024.2.2
Requires-Dist: urllib3<3.0.0,>=2.5.0
Requires-Dist: PyYAML<7.0.0,>=6.0.1
Requires-Dist: jsonschema<5.0.0,>=4.21.1
Provides-Extra: develop
Requires-Dist: pre-commit; extra == "develop"
Requires-Dist: pytest; extra == "develop"
Requires-Dist: pytest-cov; extra == "develop"
Requires-Dist: ruff; extra == "develop"
Provides-Extra: rtd
Requires-Dist: sphinx; extra == "rtd"
Dynamic: license-file
